cdmi_cli
