Metadata-Version: 1.1
Name: cdmi-client
Version: 0.3
Summary: Interactive command line client for CDMI
Home-page: https://github.com/indigo-dc/cdmi_client
Author: bertl4398
Author-email: bertl4398@googlemail.com
License: BSD
Keywords: cdmi client qos
Platform: UNKNOWN
Classifier: Development Status :: 3 - Alpha
Classifier: Environment :: Console
Classifier: License :: OSI Approved :: BSD License
Classifier: Programming Language :: Python :: 2.7
Classifier: Topic :: Internet
